mkpipe_loader_redshift/__init__.py
mkpipe_loader_redshift/jars/com.amazon.redshift_redshift-jdbc42-2.1.0.31.jar
mkpipe_loader_redshift-0.1.0.dist-info/LICENSE
mkpipe_loader_redshift-0.1.0.dist-info/METADATA
mkpipe_loader_redshift-0.1.0.dist-info/WHEEL
mkpipe_loader_redshift-0.1.0.dist-info/entry_points.txt
mkpipe_loader_redshift-0.1.0.dist-info/top_level.txt
mkpipe_loader_redshift-0.1.0.dist-info/RECORD
